bademoji/__init__.py
bademoji/emojify.py
bademoji-0.0.1.dist-info/LICENSE
bademoji-0.0.1.dist-info/METADATA
bademoji-0.0.1.dist-info/WHEEL
bademoji-0.0.1.dist-info/top_level.txt
bademoji-0.0.1.dist-info/RECORD
