Metadata-Version: 2.1
Name: bademoji
Version: 0.0.1
Summary: A small package for ruining projects
Author-email: InvisibleOne <epicsharkmods@gmail.com>
License: MIT License        
Project-URL: Homepage, https://theflamongo.com
Project-URL: Bug Tracker, https://theflamongo.com/contact
Classifier: Programming Language :: Python :: 3
Classifier: License :: OSI Approved :: MIT License
Classifier: Operating System :: OS Independent
Requires-Python: >=3.7
License-File: LICENSE
